{
  "nodes": [
    {"id": 0, "function": "workflow.get_bulk_structure"},
    {"id": 1, "function": "workflow.calculate_qe"},
    {"id": 2, "function": "workflow.generate_structures"},
    {"id": 3, "function": "workflow.calculate_qe"},
    {"id": 4, "function": "workflow.calculate_qe"},
    {"id": 5, "function": "workflow.calculate_qe"},
    {"id": 6, "function": "workflow.calculate_qe"},
    {"id": 7, "function": "workflow.calculate_qe"},
    {"id": 8, "function": "workflow.plot_energy_volume_curve"},
    {"id": 9, "value": "Al"},
    {"id": 10, "value": 4.05},
    {"id": 11, "value": true},
    {"id": 12, "value": "mini"},
    {"id": 13, "function": "python_workflow_definition.shared.get_dict"},
    {"id": 14, "value": {"Al": "Al.pbe-n-kjpaw_psl.1.0.0.UPF"}},
    {"id": 15, "value": [3, 3, 3]},
    {"id": 16, "value": "vc-relax"},
    {"id": 17, "value": 0.02},
    {"id": 18, "value": [0.9, 0.95, 1.0, 1.05, 1.1]},
    {"id": 19, "value": "strain_0"},
    {"id": 20, "function": "python_workflow_definition.shared.get_dict"},
    {"id": 21, "value": "scf"},
    {"id": 22, "value": "strain_1"},
    {"id": 23, "function": "python_workflow_definition.shared.get_dict"},
    {"id": 24, "value": "strain_2"},
    {"id": 25, "function": "python_workflow_definition.shared.get_dict"},
    {"id": 26, "value": "strain_3"},
    {"id": 27, "function": "python_workflow_definition.shared.get_dict"},
    {"id": 28, "value": "strain_4"},
    {"id": 29, "function": "python_workflow_definition.shared.get_dict"},
    {"id": 30, "function": "python_workflow_definition.shared.get_list"},
    {"id": 31, "function": "python_workflow_definition.shared.get_list"}
  ],
  "edges": [
    {"target": 0, "targetPort": "element", "source": 9, "sourcePort": null},
    {"target": 0, "targetPort": "a", "source": 10, "sourcePort": null},
    {"target": 0, "targetPort": "cubic", "source": 11, "sourcePort": null},
    {"target": 1, "targetPort": "working_directory", "source": 12, "sourcePort": null},
    {"target": 13, "targetPort": "structure", "source": 0, "sourcePort": null},
    {"target": 13, "targetPort": "pseudopotentials", "source": 14, "sourcePort": null},
    {"target": 13, "targetPort": "kpts", "source": 15, "sourcePort": null},
    {"target": 13, "targetPort": "calculation", "source": 16, "sourcePort": null},
    {"target": 13, "targetPort": "smearing", "source": 17, "sourcePort": null},
    {"target": 1, "targetPort": "input_dict", "source": 13, "sourcePort": null},
    {"target": 2, "targetPort": "structure", "source": 1, "sourcePort": "structure"},
    {"target": 2, "targetPort": "strain_lst", "source": 18, "sourcePort": null},
    {"target": 3, "targetPort": "working_directory", "source": 19, "sourcePort": null},
    {"target": 20, "targetPort": "structure", "source": 2, "sourcePort": "s_0"},
    {"target": 20, "targetPort": "pseudopotentials", "source": 14, "sourcePort": null},
    {"target": 20, "targetPort": "kpts", "source": 15, "sourcePort": null},
    {"target": 20, "targetPort": "calculation", "source": 21, "sourcePort": null},
    {"target": 20, "targetPort": "smearing", "source": 17, "sourcePort": null},
    {"target": 3, "targetPort": "input_dict", "source": 20, "sourcePort": null},
    {"target": 4, "targetPort": "working_directory", "source": 22, "sourcePort": null},
    {"target": 23, "targetPort": "structure", "source": 2, "sourcePort": "s_1"},
    {"target": 23, "targetPort": "pseudopotentials", "source": 14, "sourcePort": null},
    {"target": 23, "targetPort": "kpts", "source": 15, "sourcePort": null},
    {"target": 23, "targetPort": "calculation", "source": 21, "sourcePort": null},
    {"target": 23, "targetPort": "smearing", "source": 17, "sourcePort": null},
    {"target": 4, "targetPort": "input_dict", "source": 23, "sourcePort": null},
    {"target": 5, "targetPort": "working_directory", "source": 24, "sourcePort": null},
    {"target": 25, "targetPort": "structure", "source": 2, "sourcePort": "s_2"},
    {"target": 25, "targetPort": "pseudopotentials", "source": 14, "sourcePort": null},
    {"target": 25, "targetPort": "kpts", "source": 15, "sourcePort": null},
    {"target": 25, "targetPort": "calculation", "source": 21, "sourcePort": null},
    {"target": 25, "targetPort": "smearing", "source": 17, "sourcePort": null},
    {"target": 5, "targetPort": "input_dict", "source": 25, "sourcePort": null},
    {"target": 6, "targetPort": "working_directory", "source": 26, "sourcePort": null},
    {"target": 27, "targetPort": "structure", "source": 2, "sourcePort": "s_3"},
    {"target": 27, "targetPort": "pseudopotentials", "source": 14, "sourcePort": null},
    {"target": 27, "targetPort": "kpts", "source": 15, "sourcePort": null},
    {"target": 27, "targetPort": "calculation", "source": 21, "sourcePort": null},
    {"target": 27, "targetPort": "smearing", "source": 17, "sourcePort": null},
    {"target": 6, "targetPort": "input_dict", "source": 27, "sourcePort": null},
    {"target": 7, "targetPort": "working_directory", "source": 28, "sourcePort": null},
    {"target": 29, "targetPort": "structure", "source": 2, "sourcePort": "s_4"},
    {"target": 29, "targetPort": "pseudopotentials", "source": 14, "sourcePort": null},
    {"target": 29, "targetPort": "kpts", "source": 15, "sourcePort": null},
    {"target": 29, "targetPort": "calculation", "source": 21, "sourcePort": null},
    {"target": 29, "targetPort": "smearing", "source": 17, "sourcePort": null},
    {"target": 7, "targetPort": "input_dict", "source": 29, "sourcePort": null},
    {"target": 30, "targetPort": "0", "source": 3, "sourcePort": "volume"},
    {"target": 30, "targetPort": "1", "source": 4, "sourcePort": "volume"},
    {"target": 30, "targetPort": "2", "source": 5, "sourcePort": "volume"},
    {"target": 30, "targetPort": "3", "source": 6, "sourcePort": "volume"},
    {"target": 30, "targetPort": "4", "source": 7, "sourcePort": "volume"},
    {"target": 8, "targetPort": "volume_lst", "source": 30, "sourcePort": null},
    {"target": 31, "targetPort": "0", "source": 3, "sourcePort": "energy"},
    {"target": 31, "targetPort": "1", "source": 4, "sourcePort": "energy"},
    {"target": 31, "targetPort": "2", "source": 5, "sourcePort": "energy"},
    {"target": 31, "targetPort": "3", "source": 6, "sourcePort": "energy"},
    {"target": 31, "targetPort": "4", "source": 7, "sourcePort": "energy"},
    {"target": 8, "targetPort": "energy_lst", "source": 31, "sourcePort": null}
  ]
}